langgate/core/__init__.py
langgate/core/fields.py
langgate/core/logging.py
langgate/core/models.py
langgate/core/py.typed
langgate/core/data/default_config.yaml
langgate/core/schemas/__init__.py
langgate/core/schemas/config.py
langgate/core/utils/__init__.py
langgate/core/utils/config_utils.py
langgate_core-0.3.3.dist-info/METADATA
langgate_core-0.3.3.dist-info/WHEEL
langgate_core-0.3.3.dist-info/RECORD
