Metadata-Version: 2.4
Name: langgate-core
Version: 0.3.3
Summary: Core models and utilities for LangGate
Author: Tanantor Ltd.
Maintainer-email: Saran Connoly <saran@tanantor.com>
License: MIT
Requires-Python: >=3.13
Requires-Dist: pydantic<3.0.0,>=2.10.6
Requires-Dist: structlog<26.0.0,>=25.2.0
